pynigeria/__init__.py
pynigeria/core.py
pynigeria/data/lgas.json
pynigeria/data/settlements.json
pynigeria/data/states.json
pynigeria/exceptions.py
pynigeria/loader.py
pynigeria/models.py
pynigeria-1.2.2.dist-info/WHEEL
pynigeria-1.2.2.dist-info/entry_points.txt
pynigeria-1.2.2.dist-info/METADATA
pynigeria-1.2.2.dist-info/RECORD
