Metadata-Version: 2.3
Name: pynigeria
Version: 1.2.2
Summary: Accurate and up-to-date data on Nigerian states, LGAs, cities, towns, and villages
Author: GrandGale Technologies
Author-email: GrandGale Technologies <admin@grandgale.tech>
Requires-Dist: build>=1.3.0
Requires-Dist: pre-commit>=4.3.0
Requires-Dist: pydantic>=2.12.3
Requires-Dist: pytest>=8.4.2
Requires-Dist: ruff>=0.14.3
Requires-Dist: twine>=6.2.0
Requires-Dist: ty>=0.0.1a25
Requires-Python: >=3.12
